psy_llm_chat/__init__.py
psy_llm_chat/claude.py
psy_llm_chat/falcon.py
psy_llm_chat/gpt.py
psy_llm_chat/llama.py
psy_llm_chat/mistral.py
psy_llm_chat-0.1.4.dist-info/METADATA
psy_llm_chat-0.1.4.dist-info/WHEEL
psy_llm_chat-0.1.4.dist-info/top_level.txt
psy_llm_chat-0.1.4.dist-info/RECORD
