Metadata-Version: 2.1
Name: psy-llm-chat
Version: 0.1.4
Summary: A Package for chatting with LLMs
Home-page: https://github.com/cbjrobertson/llm_chat
Author: Cole Robertson
Author-email: cbjrobertson@gmail.com
License: UNKNOWN
Platform: UNKNOWN
Classifier: Programming Language :: Python :: 3
Classifier: License :: OSI Approved :: MIT License
Classifier: Operating System :: OS Independent
